{
  "absorb_width_bits": 128,
  "aead_core_count": 4,
  "constant_time_decrypt_failure": true,
  "constant_time_tag_compare": true,
  "context_count": 48,
  "context_interleaving_required": true,
  "context_profile": "fpga_bram_lutram",
  "context_storage": "fpga_lutram_context_memory",
  "context_storage_estimate": {
    "area_class": "medium_fpga_memory_backed",
    "context_count": 48,
    "contexts_per_engine": 12,
    "interleave_depth": 12,
    "memory_bits": 15360,
    "notes": [
      "maps naturally to FPGA LUTRAM/BRAM session storage",
      "requires at least 12 active contexts per engine for full interleave utilization",
      "context id width: 6 bits"
    ],
    "profile": "fpga_bram_lutram",
    "scheduling_class": "dynamic_or_static_multisession",
    "state_bits_total": 15360,
    "state_register_equivalent_bits": 0,
    "storage": "fpga_lutram_context_memory"
  },
  "contexts_per_engine": 12,
  "contexts_per_pipeline": 12,
  "control_axi_stream_command_channels": 3,
  "control_command_fifo_depth": 32,
  "control_csr_register_count": 0,
  "control_estimate": {
    "area_class": "high",
    "flexibility_class": "very_high",
    "notes": "Best fit for multi-context/pipelined FPGA engines supporting several modes.",
    "profile": "axi_stream_microcoded_hybrid",
    "recommended_target": "fpga",
    "scheduler_class": "stream_scheduler_plus_microcode"
  },
  "control_microcode_words": 256,
  "control_profile": "axi_stream_microcoded_hybrid",
  "control_scheduler_required": true,
  "control_supports_concurrent_modes": true,
  "control_supports_descriptors": true,
  "control_supports_dma": false,
  "control_supports_runtime_algorithm_select": true,
  "data_bus_bits": 512,
  "datapath_estimate": {
    "absorb128_cycles": 1,
    "absorb64_cycles": 1,
    "area_class": "medium_high",
    "io_fit": "excellent_when_external_bus_is_128b_or_wider",
    "key128_cycles": 1,
    "notes": [],
    "performance_class": "best_single_engine",
    "state320_cycles": 3,
    "tag128_cycles": 1
  },
  "datapath_profile": "128_bit",
  "decryption_release_policy": "buffer_until_tag_verify",
  "duplicate_compute_check": true,
  "duplicate_control_fsm_checks": true,
  "engine_count": 4,
  "expected_parallel_operations": 4,
  "fault_detection": "duplicate_compute",
  "interleave_depth": 12,
  "io_word_width_bits": 128,
  "lane_width_bits": 128,
  "padding_estimate": {
    "area_class": "medium",
    "flexibility_class": "high",
    "notes": [
      "each final stream beat carries a byte-valid mask; the core pads only the invalid tail",
      "best fit for AXI-stream style valid/ready datapaths and packetized FPGA traffic"
    ],
    "profile": "streaming_final_bytemask",
    "recommended_target": "fpga_streaming_default",
    "requires_final_bytemask": true,
    "requires_total_length": false,
    "streaming_efficiency": "excellent_streaming"
  },
  "padding_final_bytemask": true,
  "padding_final_bytemask_width": 64,
  "padding_length_handling": "streaming_final_bytemask",
  "padding_pad_in_core": true,
  "padding_profile": "streaming_final_bytemask",
  "padding_requires_total_length": false,
  "padding_strategy": "inline_combinational",
  "padding_supports_arbitrary_byte_lengths": true,
  "padding_supports_partial_blocks": true,
  "padding_tracks_byte_count": false,
  "permutation_latency": {
    "area_class": "large",
    "contexts_for_full_pipeline": 12,
    "initiation_interval": 1,
    "notes": [
      "requires context interleaving or independent messages for full utilization"
    ],
    "p12_cycles": 12,
    "p6_cycles": 6,
    "p8_cycles": 8,
    "throughput_model": "one permutation can be launched every initiation interval when enough independent contexts exist",
    "timing_risk": "medium"
  },
  "permutation_pipeline_count": 4,
  "permutation_style": "round_pipelined",
  "pipeline_initiation_interval": 1,
  "pipeline_stages": 12,
  "plaintext_buffer_capacity_bytes": 65536,
  "plaintext_buffer_storage": "bram_fifo",
  "plaintext_buffer_until_tag_verified": true,
  "randomized_counter_hardening": true,
  "rounds_per_cycle": 1,
  "sbox_columns_per_cycle": 64,
  "sbox_style": "lut5",
  "security_estimate": {
    "area_class": "approximately_2x_compute_plus_buffer",
    "fault_detection_class": "duplicate_compute",
    "notes": "FPGA baseline: duplicate computation fault detection, counter hardening, and constant-time tag compare.",
    "performance_impact": "slower_or_double_resources",
    "plaintext_buffer_area": "large_bram_fifo",
    "plaintext_release_policy": "buffer_until_tag_verify",
    "profile": "fpga_fault_detect_rand_counter_consttime_tag",
    "side_channel_class": "unmasked"
  },
  "security_profile": "fpga_fault_detect_rand_counter_consttime_tag",
  "serialized_absorb": false,
  "serialized_state_update": false,
  "shadow_state": false,
  "shared_pipeline_across_contexts": true,
  "side_channel_protection": "none",
  "state_memory_read_ports": 1,
  "state_memory_write_ports": 1,
  "top_level_estimate": {
    "aead_core_count": 4,
    "area_class": "very_high",
    "context_count": 48,
    "contexts_per_pipeline": 12,
    "expected_parallel_operations": 4,
    "notes": [
      "multiple permutation pipelines consume contexts in parallel",
      "12 contexts are assigned per permutation pipeline",
      "4 permutation pipelines are instantiated",
      "total visible contexts: 48"
    ],
    "permutation_pipeline_count": 4,
    "profile": "m_pipelines_n_contexts",
    "scheduling_class": "multi_pipeline_context_scheduler",
    "throughput_class": "extreme_context_interleaved_pipeline_parallelism"
  },
  "top_level_profile": "m_pipelines_n_contexts",
  "total_decrypt_datapaths": 4,
  "total_encrypt_datapaths": 4,
  "zeroize_plaintext_buffer_on_failure": true
}
